setup.py
aetos_serialiser/__init__.py
aetos_serialiser/expection.py
aetos_serialiser/helpers.py
aetos_serialiser/samples.py
aetos_serialiser/serialisers.py
aetos_serialiser/versioning.py
aetos_serialiser.egg-info/PKG-INFO
aetos_serialiser.egg-info/SOURCES.txt
aetos_serialiser.egg-info/dependency_links.txt
aetos_serialiser.egg-info/not-zip-safe
aetos_serialiser.egg-info/top_level.txt