Metadata-Version: 1.0
Name: aetos-serialiser
Version: 1.0.1
Summary: Simple Serialiser for Simple Developers
Home-page: https://github.com/FerrumAquila/aetos_serialiser
Author: ironeagle
Author-email: visheshbangotra@gmail.com
License: MIT
Platform: UNKNOWN
